aiopayme/__init__.py
aiopayme-0.0.1.dist-info/METADATA
aiopayme-0.0.1.dist-info/WHEEL
aiopayme-0.0.1.dist-info/RECORD
