Metadata-Version: 2.4
Name: aiopayme
Version: 0.0.1
Summary: Async Payme SDK for Python
Author-email: "@pywave" <pywave@mail.ru>
License: MIT
